jsonbasedb/__init__.py
jsonbasedb/db_models.py
jsonbasedb/utils.py
jsonbasedb-1.2.1.dist-info/LICENSE
jsonbasedb-1.2.1.dist-info/METADATA
jsonbasedb-1.2.1.dist-info/WHEEL
jsonbasedb-1.2.1.dist-info/top_level.txt
jsonbasedb-1.2.1.dist-info/RECORD
