Metadata-Version: 2.1
Name: jsonbasedb
Version: 1.2.1
Summary: A simple library for interacting with jsonbase
Home-page: https://github.com/BlitzJB/jsonbasedb
Author: BlitzJB
Author-email: blitz04.dev@gmail.com
License: UNKNOWN
Keywords: python,json,database,jsonbase
Platform: UNKNOWN
License-File: LICENSE
Requires-Dist: requests
